<annotation>
	<folder>JPEGImages</folder>
	<filename>face49.jpg</filename>
	<path>/home/huzixuan/桌面/JPEGImages/face49.jpg</path>
	<source>
		<database>Unknown</database>
	</source>
	<size>
		<width>330</width>
		<height>381</height>
		<depth>3</depth>
	</size>
	<segmented>0</segmented>
	<object>
		<name>unmask</name>
		<pose>Unspecified</pose>
		<truncated>0</truncated>
		<difficult>0</difficult>
		<bndbox>
			<xmin>55</xmin>
			<ymin>113</ymin>
			<xmax>257</xmax>
			<ymax>346</ymax>
		</bndbox>
	</object>
</annotation>
