<annotation>
	<folder>JPEGImages</folder>
	<filename>face31.jpg</filename>
	<path>/home/huzixuan/桌面/JPEGImages/face31.jpg</path>
	<source>
		<database>Unknown</database>
	</source>
	<size>
		<width>424</width>
		<height>600</height>
		<depth>3</depth>
	</size>
	<segmented>0</segmented>
	<object>
		<name>unmask</name>
		<pose>Unspecified</pose>
		<truncated>0</truncated>
		<difficult>0</difficult>
		<bndbox>
			<xmin>113</xmin>
			<ymin>133</ymin>
			<xmax>299</xmax>
			<ymax>354</ymax>
		</bndbox>
	</object>
</annotation>
