<annotation>
	<folder>JPEGImages</folder>
	<filename>masks_0076.jpg</filename>
	<path>/home/huzixuan/桌面/JPEGImages/masks_0076.jpg</path>
	<source>
		<database>Unknown</database>
	</source>
	<size>
		<width>683</width>
		<height>1024</height>
		<depth>3</depth>
	</size>
	<segmented>0</segmented>
	<object>
		<name>mask</name>
		<pose>Unspecified</pose>
		<truncated>0</truncated>
		<difficult>0</difficult>
		<bndbox>
			<xmin>231</xmin>
			<ymin>238</ymin>
			<xmax>464</xmax>
			<ymax>393</ymax>
		</bndbox>
	</object>
</annotation>
