<annotation>
	<folder>JPEGImages</folder>
	<filename>masks_0017.jpg</filename>
	<path>/home/huzixuan/桌面/JPEGImages/masks_0017.jpg</path>
	<source>
		<database>Unknown</database>
	</source>
	<size>
		<width>500</width>
		<height>722</height>
		<depth>3</depth>
	</size>
	<segmented>0</segmented>
	<object>
		<name>mask</name>
		<pose>Unspecified</pose>
		<truncated>0</truncated>
		<difficult>0</difficult>
		<bndbox>
			<xmin>168</xmin>
			<ymin>237</ymin>
			<xmax>268</xmax>
			<ymax>331</ymax>
		</bndbox>
	</object>
	<object>
		<name>mask</name>
		<pose>Unspecified</pose>
		<truncated>0</truncated>
		<difficult>0</difficult>
		<bndbox>
			<xmin>354</xmin>
			<ymin>260</ymin>
			<xmax>429</xmax>
			<ymax>313</ymax>
		</bndbox>
	</object>
	<object>
		<name>mask</name>
		<pose>Unspecified</pose>
		<truncated>0</truncated>
		<difficult>0</difficult>
		<bndbox>
			<xmin>91</xmin>
			<ymin>201</ymin>
			<xmax>141</xmax>
			<ymax>237</ymax>
		</bndbox>
	</object>
</annotation>
